localmail/__init__.py
localmail/cred.py
localmail/http.py
localmail/imap.py
localmail/inbox.py
localmail/smtp.py
localmail/templates/index.html
localmail-0.5.0.dist-info/METADATA
localmail-0.5.0.dist-info/RECORD
localmail-0.5.0.dist-info/WHEEL
localmail-0.5.0.dist-info/top_level.txt
twisted/plugins/__init__.py
twisted/plugins/localmail_tap.py
