Metadata-Version: 2.1
Name: localmail
Version: 0.5.0
Summary: Test SMTP/IMAP server for local integration testing
Home-page: https://launchpad.net/localmail
Author: Simon Davy
Author-email: simon.davy@canonical.com
License: GPLv3
Platform: UNKNOWN
Classifier: Development Status :: 4 - Beta
Classifier: Environment :: Console
Classifier: Framework :: Twisted
Classifier: License :: OSI Approved :: GNU General Public License v3 (GPLv3)
Classifier: Intended Audience :: Developers
Classifier: Operating System :: POSIX
Classifier: Programming Language :: Python :: 2.7
Classifier: Programming Language :: Python :: 3.5
Classifier: Programming Language :: Python :: 3.6
Classifier: Programming Language :: Python :: Implementation :: CPython
Classifier: Programming Language :: Python :: Implementation :: PyPy
Classifier: Topic :: Communications :: Email
Classifier: Topic :: Communications :: Email :: Mail Transport Agents
Classifier: Topic :: Communications :: Email :: Post-Office :: IMAP
Classifier: Topic :: Software Development :: Testing
Requires-Dist: Twisted (>=11.0.0)
Requires-Dist: jinja2 (>=2.0.0)
